net_access/__init__.py
net_access/main.py
net_access_whu-0.4.4.dist-info/DESCRIPTION.rst
net_access_whu-0.4.4.dist-info/METADATA
net_access_whu-0.4.4.dist-info/RECORD
net_access_whu-0.4.4.dist-info/WHEEL
net_access_whu-0.4.4.dist-info/entry_points.txt
net_access_whu-0.4.4.dist-info/metadata.json
net_access_whu-0.4.4.dist-info/top_level.txt
