Metadata-Version: 2.0
Name: net-access-whu
Version: 0.4.4
Summary: 终端登录武汉大学校园网, 国软IIS-WEB
Home-page: https://github.com/hellflame/WHU-net-access
Author: hellflame
Author-email: hellflamedly@gmail.com
License: Apache License
Keywords: network auth,WHU
Platform: all
Classifier: Development Status :: 5 - Production/Stable
Classifier: Intended Audience :: Developers
Classifier: Programming Language :: Python
Classifier: Programming Language :: Python :: 2 :: Only
Classifier: Environment :: Console
Classifier: License :: OSI Approved :: Apache Software License
Classifier: Operating System :: OS Independent
